pytorch_mixtures/__init__.py
pytorch_mixtures/mod_layer.py
pytorch_mixtures/moe_layer.py
pytorch_mixtures/routing.py
pytorch_mixtures/utils.py
pytorch_mixtures-0.1.0.dist-info/LICENSE
pytorch_mixtures-0.1.0.dist-info/METADATA
pytorch_mixtures-0.1.0.dist-info/WHEEL
pytorch_mixtures-0.1.0.dist-info/top_level.txt
pytorch_mixtures-0.1.0.dist-info/RECORD
