Metadata-Version: 2.1
Name: pytorch-mixtures
Version: 0.1.0
Summary: The one-stop solution to easily integrate MoE & MoD layers into custom PyTorch code.
Home-page: https://github.com/jaisidhsingh/pytorch-mixtures
Author: Jaisidh Singh
Author-email: jaisidhsingh@gmail.com
License: UNKNOWN
Platform: UNKNOWN
Classifier: Programming Language :: Python :: 3
Classifier: License :: OSI Approved :: MIT License
Classifier: Operating System :: OS Independent
Requires-Python: >=3.8
License-File: LICENSE
Requires-Dist: torch (==2.2.2)
Requires-Dist: einops (==0.8.0)
